LICENSE.txt
MANIFEST.in
README.md
requirements.txt
setup.cfg
setup.py
panther_detection_helpers/__init__.py
panther_detection_helpers/caching.py
panther_detection_helpers/mocking.py
panther_detection_helpers/monitoring.py
panther_detection_helpers.egg-info/PKG-INFO
panther_detection_helpers.egg-info/SOURCES.txt
panther_detection_helpers.egg-info/dependency_links.txt
panther_detection_helpers.egg-info/requires.txt
panther_detection_helpers.egg-info/top_level.txt
tests/test_caching.py
tests/test_mocking.py