Metadata-Version: 2.2
Name: panther_detection_helpers
Version: 0.5.0
Summary: Panther Detection Helpers Library
Home-page: https://github.com/panther-labs/panther_detection_helpers
Download-URL: https://github.com/panther-labs/panther_detection_helpers/archive/refs/tags/v0.5.0.tar.gz
Author: Panther Labs Inc
Author-email: pypi@runpanther.io
License: AGPL-3.0
Keywords: Security,CLI
Classifier: Topic :: Security
Classifier: Development Status :: 4 - Beta
Classifier: Intended Audience :: Developers
Classifier: Programming Language :: Python :: 3.11
Classifier: License :: OSI Approved :: GNU Affero General Public License v3
License-File: LICENSE.txt
Requires-Dist: jsonpath-ng
Requires-Dist: datadog
Dynamic: author
Dynamic: author-email
Dynamic: classifier
Dynamic: download-url
Dynamic: home-page
Dynamic: keywords
Dynamic: license
Dynamic: requires-dist
Dynamic: summary
